<?xml version="1.0" encoding="utf-8" ?>
<localizationDictionary culture="km">
	<texts>
		<text name="HomePage" value="ទំព័រដើម" />
		<text name="About" value="អំពី" />
		<text name="WelcomeMessage" value="សូមស្វាគមន៍មកកាន់ {0}!" />
		<text name="Welcome" value="សូមស្វាគមន៍" />
		<text name="FormIsNotValidMessage" value="បែបបទមិនត្រឹមត្រូវ សូមពិនិត្យនិងកែតម្រូវឡើងវិញ។" />
		<text name="TenantNameCanNotBeEmpty" value="Tenant name can not be empty" />
		<text name="InvalidUserNameOrPassword" value="Invalid user name or password" />
		<text name="ThereIsNoTenantDefinedWithName{0}" value="There is no tenant defined with name {0}" />
		<text name="TenantIsNotActive" value="Tenant {0} មិនមានសុពលភាព." />
		<text name="UserIsNotActiveAndCanNotLogin" value="អ្នកប្រើប្រាស់ {0} មិនមានសុពលភាព មិនអាចចូលបានឡើយ." />
		<text name="UserEmailIsNotConfirmedAndCanNotLogin">Your email address is not confirmed. You can not login.</text>
		<text name="UserLockedOutMessage">The user account has been locked out. Please try again later.</text>
		<text name="PleaseEnterLoginInformation" value="សូមបញ្ចូលព័ត៌មានចូល" />
		<text name="TenancyName" value="ឈ្មោះអ្នកជាវ" />
		<text name="UserNameOrEmail" value="ឈ្មោះអ្នកប្រើប្រាស់ ឬអ៊ីម៉ែល" />
		<text name="Password" value="លេខសម្ងាត់" />
		<text name="ResetPassword" value="ប្ដូរលេខសម្ងាត់" />
		<text name="UpdatePassword" value="កែប្រែលេខសម្ងាត់" />
		<text name="ForgotPassword" value="ភ្លេចលេខសម្ងាត់" />
		<text name="RememberMe" value="ចំណាំខ្ញុំ" />
		<text name="LogIn" value="ចូល" />
		<text name="LoginFailed" value="ចូលបរាជ័យ!" />
		<text name="NameSurname" value="គោត្តនាម នាម" />
		<text name="UserName" value="ឈ្មោះអ្នកប្រើប្រាស់" />
		<text name="Name" value="ឈ្មោះ" />
		<text name="Surname" value="ត្រកូល" />
		<text name="EmailAddress" value="អាសយដ្ឋានអ៊ីម៉ែល" />
		<text name="Tenants" value="អ្នកជាវ" />
		<text name="Tenant" value="អ្នកជាវ" />
		<text name="SavedSuccessfully" value="រក្សាទុកជោគជ័យ" />
		<text name="CreateNewTenant" value="បង្កើតអ្នកជាវថ្មី" />
		<text name="AdminEmailAddress" value="អ៊ីម៉ែល Admin" />
		<text name="AdminPassword" value="លេខសម្ងាត់ Admin" />
		<text name="Save" value="រក្សាទុក" />
		<text name="Cancel" value="បោះបង់" />
		<text name="TenantName_Regex_Description" value="Tenant name must be at least 2 chars, starts with a letter and continue with letter, number, dash or underscore." />
		<text name="DefaultPasswordIs" value="Default password is {0}" />
		<text name="CanBeEmptyToLoginAsHost" value="Can be empty to login as host." />
		<text name="Register" value="ចុះឈ្មោះ" />
		<text name="OrLoginWith" value="Or login with" />
		<text name="WaitingForActivationMessage" value="Your account is waiting to be activated by system admin." />
		<text name="TenantSelection" value="Tenant Selection" />
		<text name="TenantSelection_Detail" value="Please select one of the following tenants." />
		<text name="Logout" value="ចេញ" />
		<text name="RegisterFormUserNameInvalidMessage">Please don't enter an email address for username.</text>
		<text name="DatabaseConnectionString" value="Database connection string" />
		<text name="Users" value="អ្នកប្រើប្រាស់" />
		<text name="User" value="អ្នកប្រើប្រាស់" />
		<text name="IsActive" value="សុពលភាព" />
		<text name="FullName" value="ឈ្មោះពេញ" />
		<text name="CreateNewUser" value="បង្កើតអ្នកប្រើប្រាស់ថ្មី" />
		<text name="Yes" value="បាទ/ចាស" />
		<text name="No" value="ទេ" />
		<text name="Optional" value="Optional" />
		<text name="LeaveEmptyToSwitchToHost">Leave empty to switch to the host</text>
		<text name="CurrentTenant">អ្នកជាវបច្ចុប្បន្ន</text>
		<text name="NotSelected">មិនបានជ្រើសរើស</text>
		<text name="Change">ប្ដូរ</text>
		<text name="ChangeTenant">ប្ដូរអ្នកជាវ</text>
		<text name="MultiLevelMenu">Multi Level Menu</text>
		<text name="Back">ថយក្រោយ</text>
		<text name="SuccessfullyRegistered">Successfully registered</text>
		<text name="WaitingForEmailActivation">Your email address should be activated</text>
		<text name="Roles">តួនាទី</text>
		<text name="DisplayName">ឈ្មោះបង្ហាញ</text>
		<text name="Edit">កែប្រែ</text>
		<text name="Delete">លុយ</text>
		<text name="CreateNewRole">បង្កើតតួនាទីថ្មី</text>
		<text name="RoleName">ឈ្មោះតួនាទី</text>
		<text name="Actions">សកម្មភាព</text>
		<text name="CouldNotCompleteLoginOperation">Could not complete login operation. Please try again later.</text>
		<text name="CouldNotValidateExternalUser">Could not validate external user</text>
		<text name="EditRole">កែប្រែសិទ្ធិ</text>
		<text name="EditTenant">កែប្រែអ្នកជាវ</text>
		<text name="EditUser">កែប្រេអ្នកប្រើប្រាស់</text>
		<text name="TenantIdIsNotActive{0}">TenantId {0} is not active</text>
		<text name="UnknownTenantId{0}">Unknown tenantId {0}</text>
		<text name="ThisFieldIsRequired">This field is required</text>
		<text name="PleaseWait">Please wait...</text>
		<text name="Administration">រដ្ឋបាលគ្រប់គ្រង</text>
		<text name="ClearAll">Clear all</text>
		<text name="ClearOthers">Clear others</text>
		<text name="LabelOptions">Label options</text>
		<text name="Permissions">សិទ្ធិ</text>
		<text name="RoleDescription">អធិប្បាយតួនាទី</text>
		<text name="Refresh">ផ្ទុកឡើងវិញ</text>
		<text name="Create">បង្កើត</text>
		<text name="UserDetails">លម្អិតអ្នកប្រើប្រាស់</text>
		<text name="UserRoles">សិទ្ធិអ្នកប្រើប្រាស់</text>
		<text name="ConfirmPassword">បញ្ជាក់លេខសម្ងាត់</text>
		<text name="Version">ជំនាន់</text>
		<text name="On">បើក</text>
		<text name="Off">បិទ</text>
		<text name="AreYouSureWantToDelete">Are you sure want to delete {0}?</text>
		<text name="SuccessfullyDeleted">Successfully deleted</text>
		<text name="StartTyping">Start Typing</text>
		<text name="Skins">Skins</text>
		<text name="Settings">កំណត់</text>
		<text name="Filter">ច្រោះ</text>
		<text name="CurrentPassword">លេខសម្ងាត់បច្ចុប្បន្ន</text>
		<text name="NewPassword">លេខសម្ងាត់ថ្មី</text>
		<text name="ConfirmNewPassword">Confirm New Password</text>
		<text name="PasswordsDoNotMatch">Passwords do not match</text>
		<text name="PasswordsMustBeAtLeast8CharactersContainLowercaseUppercaseNumber">Passwords must be at least 8 characters, contain a lowercase, uppercase, and number</text>
		<text name="UserDeleteWarningMessage">User {0} will be deleted.</text>
		<text name="RoleDeleteWarningMessage">Role {0} will be deleted and unassigned from all assigned users.</text>
		<text name="TenantDeleteWarningMessage">Tenant {0} will be deleted.</text>
		<text name="SearchWithThreeDot">Search...</text>
		<text name="PleaseEnterAtLeastNCharacter">សូមបំពេញយ៉ាងតិច {0} តួរអក្សរ</text>
		<text name="PleaseEnterNoMoreThanNCharacter">សូមបំពេញមិនឱ្យលើស {0} តួរអក្សរ</text>
		<text name="InvalidEmailAddress">អ៊ីម៉ែលមិនត្រឹមត្រូវ</text>
		<text name="InvalidPattern">គំរូមិនត្រឹមត្រូវ</text>
		<text name="PairsDoNotMatch">Do not match</text>
		<text name="All">ទាំងអស់</text>
		<text name="TotalRecordsCount">Total: {0}</text>
		<text name="Search">ស្វែងរក</text>
		<text name="Clear">សម្អាត</text>
		<text name="ResetPasswordStepOneInfo">1. Enter your administrator password</text>
		<text name="ResetPasswordStepTwoInfo">2. Copy this random password so you can send it to the user</text>
		<text name="UsersActivation">ដំនើរការអ្នកប្រើប្រាស់</text>
		<text name="PasswordIsRequired">សូមបំពេលលេខសម្ងាត់!</text>

		<text name="Editions">កញ្ជប់</text>
		<text name="Edition">កញ្ជប់</text>
		<text name="View">ពិនិត្យ</text>
		<text name="ExportExcel">ទាញយក Excel</text>
		<text name="ImportExcel">បញ្ចូលពី Excel</text>
		<text name="Import">បញ្ចូល</text>
		<text name="EditAccount">កែប្រែគណនី</text>
		<text name="SeeAccount">ឃើញគណនី</text>
		<text name="EditPrice">កែប្រែតម្លៃ</text>
		<text name="SeePrice">ឃើញតម្លៃ</text>
		<text name="EditQty">កែប្រែចំនួន</text>
		<text name="Over24Modify">កែប្រែសុពលភាពលើសពី 24 ម៉ោង</text>
		<text name="ColumnsIsRequired">ចាំបាច់ត្រូវមានតារាងជួរឈរដើម្បី {0}</text>
		<text name="SignIn">ចូល</text>
		<text name="SignUp">ចុះឈ្មោះ</text>
		<text name="SignOut">ចេញ</text>
		<text name="SendPasswordResetLink">តំណភ្ជាប់សម្រាប់ប្ដូរលេខសម្ងាត់ថ្មីនឹងត្រូវផ្ញើទៅកាន់អាសយដ្ឋានអ៊ីម៉ែលរបស់អ្នក</text>
		<text name="PasswordResetMailSentMessage">តំណភ្ជាប់សម្រាប់ប្ដូរលេខសម្ងាត់ថ្មីត្រូវបានផ្ញើទៅកាន់អ៊ីម៉ែលរបស់អ្នកដោយជោគជ័យ</text>
		<text name="MailSent">អ៊ីម៉ែលត្រូវបានផ្ញើចេញ</text>
		<text name="MyAccount">គណនីខ្ញុំ</text>
		<text name="BackToMyAccount">ត្រឡប់ទៅគណនីខ្ញុំ</text>
		<text name="ChangePassword">ប្ដូរលេខសម្ងាត់</text>
		<text name="LinkAccount">គណនីតភ្ជាប់</text>
		<text name="Profile">ប្រវត្តិរូប</text>
		<text name="ManageLinkAccount">គ្រប់គ្រងគណនីតភ្ជាប់</text>
		<text name="UserGroups">ក្រុមអ្នកប្រើប្រាស់</text>
		<text name="UserGroup">ក្រុមអ្នកប្រើប្រាស់</text>
		<text name="Notification">សេចក្តីជូនដំណឹង</text>
		<text name="AuditLogs">ប្រវត្តិប្រើប្រាស់</text>
		<text name="Dashboard">របាយការណ៍ខ្លីៗ</text>
		<text name="Home">ទំព័រដើម</text>
		<text name="Administrations">រដ្ឋបាលគ្រប់គ្រង់</text>
		<text name="Description">អធិប្បាយ</text>
		<text name="GridLine">បន្ទាត់ក្រឡា</text>
		<text name="Date">ថ្ងៃខែ</text>
		<text name="FromDate">ពីថ្ងៃ</text>
		<text name="ToDate">ដល់ថ្ងៃ</text>
		<text name="ServiceName">ឈ្មោះសេវាកម្ម</text>
		<text name="MethodName">ឈ្មោះវធីសាស្រ្ត</text>
		<text name="Browser">កម្មវិធីរុករក</text>
		<text name="Duration">រយៈពេល</text>
		<text name="MaxDuration">រយៈពេលអតិបរមា</text>
		<text name="MinDuration">រយៈពេលអប្បរមា</text>
		<text name="HasError">មានកំហុស</text>
		<text name="ExecutionTime">រយៈពេលដំណើរការ</text>
		<text name="Status">លក្ខណៈ</text>
		<text name="ClientIpAddress">អសយដ្ឋាន IP</text>
		<text name="BrowserInfo">ព័ត៌មានកម្មវិធីរុករក</text>
		<text name="Exception">កំហុសលើកលែង</text>
		<text name="LoginAsTenant">ចូលជាអ្នកជាវនេះ</text>
		<text name="RecordNotFound">មិនមានទិន្នន័យ</text>
		<text name="NotFound">{0} មិនមានក្នុងប្រព័ន្ធ</text>
		<text name="Result">លទ្ធផល</text>
		<text name="LoginAttempt">ប៉ុនប៉ងចូល</text>
		<text name="LoginTime">ម៉ោងចូល</text>
		<text name="Close">បិទ</text>
		<text name="DeleteWarningMessage">{0} "{1}" នឹងត្រូវបានលុបចោល</text>
		<text name="Language">ភាសា</text>
		<text name="Languages">ភាសា</text>
		<text name="CannotBeDeleted">{0} មិនអាចលុប</text>
		<text name="DefaultLanguage">ភាសាលំនាំដើម</text>
		<text name="LanguageTexts">ភាសាបកប្រែ</text>
		<text name="BaseValue">តម្លៃមូលដ្ឋាន</text>
		<text name="BaseLanguage">ភាសាមូលដ្ឋាន</text>
		<text name="TargetValue">តម្លៃគោលដៅ</text>
		<text name="TargetLanguage">ភាសាគោលដៅ</text>
		<text name="Source">Source</text>
		<text name="SMTPMail">អ៊ីម៉ែល SMTP</text>
		<text name="Icon">និមិត្តសញ្ញា</text>
		<text name="Enable">ដំនើរការ</text>
		<text name="Disable">ផ្អាកដំនើរការ</text>
		<text name="ChangeTexts">កែប្រែអក្សរ</text>
		<text name="SetAsDefault">ដាក់ជាលំនាំដើម</text>
		<text name="MaximumUserCount">ចំនួនអ្នកប្រើប្រាស់អតិបរមា</text>
		<text name="MaximumBranchCount">ចំនួនសាខាអតិបរាម</text>
		<text name="MaximumWarehouseCount">ចំនួនឃ្មាំងទំនិញអតិបរមា</text>
		<text name="MaximumCount">ចំនួន {0} អតិបរមា</text>
		<text name="MaximumCount_Description">0 = មិនកំណត់</text>
		<text name="MaximumCount_Error_Message">ចំនួន {0} បានកើនដល់អតិបរមាបានកំណត់!</text>
		<text name="MaximumCount_Error_Detail">ការជាវរបស់អ្នកមានចំនួនកំណត់អតិបរមាសម្រាប់ {1} ស្មើនឹង {0}.</text>
		<text name="CharacterLength">{0} តូរអក្សរ</text>
		<text name="SpecialCharacter">សញ្ញាពិសេស</text>
		<text name="Lowercase">អក្សរតូច</text>
		<text name="Uppercase">អក្សរធំ</text>
		<text name="Number">លេខ</text>
		<text name="PasswordsMustBeAtLeastContain">លេខសម្ងាត់យ៉ាងហោចណាស់ត្រូវមាន</text>
		<text name="ChangeFeatures">កែប្រែកញ្ចប់កម្មវិធី</text>
		<text name="ResetDefault">ត្រលប់ទៅលំនាំដើម</text>
		<text name="Accounting">គណនេយ្យ</text>
		<text name="Vendors">អ្នកផ្គត់ផ្គង់</text>
		<text name="Vendor">អ្នកផ្គត់ផ្គង់</text>
		<text name="Customers">អតិថិជន</text>
		<text name="Customer">អតិថិជន</text>
		<text name="Chat">ឆាត</text>
		<text name="TenantToTenant">អ្នកជាវទៅអ្នកជាវ</text>
		<text name="TenantToHost">អ្នកជាវទៅក្រុមហ៊ុន</text>
		<text name="Reports">របាយការណ៍</text>
		<text name="Report">របាយការណ៍</text>
		<text name="Company">ក្រុមហ៊ុន</text>
		<text name="MultiCurrencies">ពហុរូបិយបណ្ណ</text>
		<text name="Currency">រូបិយបណ្ណ</text>
		<text name="Currencies">រូបិយបណ្ណ</text>
		<text name="Employees">បុគ្គលិក</text>
		<text name="Employee">បុគ្គលិក</text>
		<text name="Positions">តំណែង</text>
		<text name="Position">តំណែង</text>
		<text name="Inventory">ស្តុក</text>
		<text name="Inventories">ស្តុក</text>
		<text name="File">ឯកសារ</text>
		<text name="Files">ឯកសារ</text>
		<text name="Loans">កម្ចី</text>
		<text name="Loan">កម្ចី</text>
		<text name="Payments">ទូទាត់ប្រាក់</text>
		<text name="Payment">ទូទាត់ប្រាក់</text>
		<text name="Penalties">ពិន័យ</text>
		<text name="Penalty">ពិន័យ</text>
		<text name="POS">POS</text>
		<text name="Rooms">បន្ទប់</text>
		<text name="Room">បន្ទប់</text>
		<text name="Tables">តុ</text>
		<text name="Table">តុ</text>
		<text name="SaleOrders">បញ្ជាលក់</text>
		<text name="SaleOrder">បញ្ជាលក់</text>
		<text name="Quotations">ព្រាងតម្លៃ</text>
		<text name="Quotation">ព្រាងតម្លៃ</text>
		<text name="SaleReturns">ត្រឡប់ទំនិញលក់</text>
		<text name="SaleReturn">ត្រឡប់ទំនិញលក់</text>
		<text name="SaleCommissions">កម្រៃជើងសារ</text>
		<text name="SaleCommission">កម្រៃជើងសារ</text>
		<text name="SaleRepresentatives">តំណាងលក់</text>
		<text name="SaleRepresentative">តំណាងលក់</text>
		<text name="Setup">ដំឡើង</text>
		<text name="Taxes">ពន្ធ</text>
		<text name="Tax">ពន្ធ</text>
		<text name="FindTaxes">ស្វែងរកពន្ធ</text>
		<text name="Warehouses">ឃ្លាំងទំនិញ</text>
		<text name="Warehouse">ឃ្លាំងទំនិញ</text>
		<text name="Locations">ទីតាំង</text>
		<text name="Location">ទីតាំង</text>
		<text name="Pages">ទំព័រ</text>
		<text name="OrganizationUnits">រចនាសម្ព័ន្ធ</text>
		<text name="OrganizationUnit">រចនាសម្ព័ន្ធ</text>
		<text name="HangfireDashboard">ផ្ទាំងគ្រប់គ្រង Hangfire</text>
		<text name="Permission">សិទ្ធិ</text>
		<text name="RoleInfo">ព័ត៌មានតួនាទី</text>
		<text name="Total">សរុប</text>
		<text name="Classes">ថ្នាក់</text>
		<text name="Class">ថ្នាក់</text>
		<text name="Counters">បញ្ជរ</text>
		<text name="Counter">បញ្ជរ</text>
		<text name="Banks">ធនាគារ</text>
		<text name="Bank">ធនាគារ</text>
		<text name="ChartOfAccounts">តារាងគណនី</text>
		<text name="ChartOfAccount">តារាងគណនី</text>
		<text name="Accounts">គណនី</text>
		<text name="Account">គណនី</text>
		<text name="Journals">ទិនានុប្បវត្តិ</text>
		<text name="Journal">ទិនានុប្បវត្តិ</text>
		<text name="Ledgers">សៀវភៅធំ</text>
		<text name="Ledger">សៀវភៅធំ</text>
		<text name="ProfitLoss">ចំណេញខាត</text>
		<text name="BalanceSheet">តារាងតុល្យការ</text>
		<text name="FindBranches">ស្វែងរកសាខា</text>
		<text name="Branches">សាខា</text>
		<text name="Branch">សាខា</text>
		<text name="Contracts">កិច្ចសន្យា</text>
		<text name="Contract">កិច្ចសន្យា</text>
		<text name="Invoices">វិក្កយបត្រលក់</text>
		<text name="Invoice">វិក្កយបត្រលក់</text>
		<text name="ReceivePayments">ទទួលប្រាក់</text>
		<text name="ReceivePayment">ទទួលប្រាក់</text>
		<text name="SaleTypes">ប្រភេទលក់</text>
		<text name="SaleType">ប្រភេទលក់</text>
		<text name="Groups">ក្រុម</text>
		<text name="Group">ក្រុម</text>
		<text name="Exchanges">ប្ដូរ</text>
		<text name="Exchange">ប្ដូរ</text>
		<text name="ExchangeRate">អត្រាប្ដូរប្រាក់</text>
		<text name="ExchangeRates">អត្រាប្ដូរប្រាក់</text>
		<text name="Rate">អត្រា</text>
		<text name="MembersCards">បណ្ណសមាជិក</text>
		<text name="MembersCard">បណ្ណសមាជិក</text>
		<text name="FormTemplates">ទម្រង់គំរូ</text>
		<text name="FormTemplate">ទម្រង់គំរូ</text>
		<text name="Items">ទំនិញ</text>
		<text name="Item">ទំនិញ</text>
		<text name="PaymentMethods">មធ្យោបាយទូទាត់</text>
		<text name="PaymentMethod">មធ្យោបាយទូទាត់</text>
		<text name="Regions">តំបន់</text>
		<text name="Region">តំបន់</text>
		<text name="BillPayments">បង់ប្រាក់</text>
		<text name="BillPayment">បង់ប្រាក់</text>
		<text name="Bills">វិក្កយបត្រទិញ</text>
		<text name="Bill">វិក្កយបត្រទិញ</text>
		<text name="PurchaseOrders">បញ្ជាទិញ</text>
		<text name="PurchaseOrder">បញ្ជាទិញ</text>
		<text name="PurchaseTypes">ប្រភេទទិញ</text>
		<text name="PurchaseType">ប្រភេទទិញ</text>
		<text name="AutoInventories">ស្តុកស្វ័យប្រវត្តិ</text>
		<text name="AutoInventory">ស្តុកស្វ័យប្រវត្តិ</text>
		<text name="ColorPatterns">ពណ៌ផ្ទៃ</text>
		<text name="ColorPattern">ពណ៌ផ្ទៃ</text>
		<text name="Brands">ម៉ាក</text>
		<text name="Brand">ម៉ាក</text>
		<text name="FieldAs">ជួរ A</text>
		<text name="FieldA">ជួរ A</text>
		<text name="FieldBs">ជួរ B</text>
		<text name="FieldB">ជួរ B</text>
		<text name="FieldCs">ជួរ C</text>
		<text name="FieldC">ជួរ C</text>
		<text name="Units">ខ្នាត</text>
		<text name="Unit">ខ្នាត</text>
		<text name="PriceLevels">កម្រិកថ្លៃ</text>
		<text name="PriceLevel">កម្រិកថ្លៃ</text>
		<text name="Promotions">លក់ពិសេស</text>
		<text name="Promotion">លក់ពិសេស</text>
		<text name="UseDefaultCredentials">ប្រើគណនីលំនាំដើម</text>
		<text name="Apps">កម្មវិធី</text>
		
		<text name="InterestRates">អត្រាការប្រាក់</text>
		<text name="InterestRat">អត្រាការប្រាក់</text>
		<text name="Interest">ការប្រាក់</text>
		<text name="Collaterals">ទ្រព្យបញ្ចាំ</text>
		<text name="Collateral">ទ្រព្យបញ្ចាំ</text>
		<text name="Transfers">ផ្ទេរ</text>
		<text name="Transfer">ផ្ទេរ</text>
		<text name="Issues">បញ្ចេញទំនិញ</text>
		<text name="Issue">បញ្ចេញទំនិញ</text>
		<text name="Receipts">ទទួលទំនិញ</text>
		<text name="Receipt">ទទួលទំនិញ</text>
		<text name="Alerts">រំលឹក</text>
		<text name="Alert">រំលឹក</text>
		<text name="Productions">ផលិតកម្ម</text>
		<text name="Production">ផលិតកម្ម</text>
		<text name="ProductionProcesses">សង្វាក់ផលិតកម្ម</text>
		<text name="ProductionProcess">សង្វាក់ផលិតកម្ម</text>
		<text name="ProductionOrders">បញ្ជាផលិតកម្ម</text>
		<text name="ProductionOrder">បញ្ជាផលិតកម្ម</text>
		<text name="ProductionLines">ខ្សែរសង្វាក់ផលិតកម្ម</text>
		<text name="ProductionLine">ខ្សែរសង្វាក់ផលិតកម្ម</text>
		<text name="RoomGroups">ក្រុមបន្ទប់</text>
		<text name="RoomGroup">ក្រុមបន្ទប់</text>
		<text name="TableGroups">ក្រុមតុ</text>
		<text name="TableGroup">ក្រុមតុ</text>
		<text name="SaleInvoiceDetail">វិក្កយបត្រលក់លម្អិត</text>
		<text name="SaleInvoices">វិក្កយបត្រលក់</text>
		<text name="SaleInvoice">វិក្កយបត្រលក់</text>
		<text name="Aging">Aging</text>
		<text name="CostDetail">តម្លៃលម្អិត</text>
		<text name="CostSummary">តម្លៃសង្ខេប</text>
		<text name="CustomerBorrows">អតិថិជនខ្ចី</text>
		<text name="CustomerBorrow">អតិថិជនខ្ចី</text>
		<text name="StockBalance">សមតុល្យស្តុក</text>
		<text name="Balance">សមតុល្យ</text>
		<text name="Transactions">ប្រតិបត្តិការ</text>
		<text name="Transaction">ប្រតិបត្តិការ</text>
		<text name="TransactionDetail">ប្រតិបត្តិការលម្អិត</text>
		<text name="PurchaseBills">វិក្កយបត្រទិញ</text>
		<text name="PurchaseBillDetail">វិក្កយបត្រទិញលម្អិត</text>
		<text name="Slots">ទីតាំងទំនិញ</text>
		<text name="Slot">ទីតាំងទំនិញ</text>
		<text name="Collections">ប្រមូលសំណង</text>
		<text name="Collection">ប្រមូលសំណង</text>
		<text name="RetainEarning">ប្រាក់ចំណេញរក្សាទុក</text>
		<text name="CashFlows">លំហូរសាច់ប្រាក់</text>
		<text name="CashFlow">លំហូរសាច់ប្រាក់</text>
		<text name="CashFlowDetail">លំហូរសាច់ប្រាក់លម្អិត</text>
		<text name="LoginAsUser">ចូលកម្មវិធីជាអ្នកប្រើប្រាស់នេះ</text>
		<text name="ManageOrganizationTree">គ្រប់គ្រង់រចនាសម្ព័ន្ធក្រុមហ៊ុន</text>
		<text name="ManageMembers">គ្រប់គ្រងសមាជិក</text>
		<text name="ChangePermissions">កែប្រែសិទ្ធិ</text>
		<text name="Countries">ប្រទេស</text>
		<text name="Country">ប្រទេស</text>
		<text name="CityProvinces">ខេត្តក្រុង</text>
		<text name="KhanDistricts">ស្រុងខណ្ឌ</text>
		<text name="SangkatCommunes">ឃុំសង្កាត់</text>
		<text name="Villages">ភូមិ</text>
		
		<text name="CompanySetting">កំណត់ព័ត៌មានក្រុមហ៊ុន</text>
		<text name="CompanySetup">របៀបចំព័ត៌មានក្រុមហ៊ុន</text>
		<text name="CompanyProfile">ព័ត៌មានក្រុមហ៊ុន</text>
		<text name="GeneralSetting">កំណត់ទូទៅ</text>
		<text name="DefaultSetting">កំណត់លំនាំដើម</text>
		<text name="OtherSetting">កំណត់ផ្សេងៗ</text>
		<text name="LoanList">តារាងកម្ចី</text>
		<text name="Print">បោះពុម្ព</text>
		<text name="Void">មោឃៈ</text>
		<text name="Voided">មោឃៈភាព</text>
		<text name="From">មកពី {0}</text>
		<text name="CreateDeposit">បង្កើកដាក់ប្រាក់</text>
		<text name="CreateWithdraw">បង្កើតដកប្រាក់</text>
		<text name="CreateTransfer">បង្កើតផ្ទេរ</text>
		<text name="Grades">ចំណាត់ថ្នាក់</text>
		<text name="Grade">ចំណាត់ថ្នាក់</text>
		<text name="ItemGroups">ក្រុមទំនិញ</text>
		<text name="ItemGroup">ក្រុមទំនិញ</text>
		<text name="ItemList">តារាងទំនិញ</text>
		<text name="Scores">ពិន្ទុ</text>
		<text name="Score">ពិន្ទុ</text>
		<text name="Sizes">ទំហំ</text>
		<text name="Size">ទំហំ</text>
		<text name="WeightUnits">ខ្នាត់ទម្ងន់</text>
		<text name="Weight">ទម្ងន់</text>
		<text name="NetWeight">ទម្ងន់សុទ្ធ</text>
		<text name="GrossWeight">ទម្ងន់សរុប</text>
		<text name="EmployeeList">តារាងបុគ្គលិក</text>
		<text name="ChangeMembers">ផ្លាស់ប្ដូរសមាជិក</text>
		<text name="InventoryReports">របាយការណ៍ស្តុក</text>
		<text name="ModifyAllTemplates">កែប្រែគ្រប់ទម្រង់គំរូ</text>
		<text name="See">ឃើញ</text>
		<text name="Balances">សមតុល្យ</text>
		<text name="CreateTemplate">បង្កើតទម្រង់គំរូ</text>
		<text name="ModifyTemplate">កែប្រែទម្រង់គំរូ</text>
		<text name="TrialBalance">តារាងតុល្យភាព</text>
		<text name="CustomerAging">សមតុល្យអតិថិជនតាមកាល</text>
		<text name="VendorAging">សមតុល្យអ្នកផ្គត់ផ្គង់តាមកាល</text>
		<text name="Adjustments">កែតម្រូវ</text>
		<text name="CustomerBorrowReturns">អតិថិជនសងទំនិញ</text>
		<text name="Others">ផ្សេងៗ</text>
		<text name="Purchases">ទិញ</text>
		<text name="PurchaseReturns">ត្រលប់ទំនិញទិញ</text>
		<text name="CustomerGroups">ក្រុមអតិថិជន</text>
		<text name="CustomerGroup">ក្រុមអតិថិជន</text>
		<text name="CustomerList">តារាងអតិថិជន</text>
		<text name="ContractAlerts">ជូនដំណឹងកិច្ចសន្យា</text>
		<text name="ConvertToInvoice">បំប្លែងជាវិក្កយបត្រ</text>
		<text name="FromContract">មកពីកិច្ចសន្យា</text>
		<text name="FromQuotation">មកពីព្រាងតម្លៃ</text>
		<text name="FromOrder">មកពីការបញ្ច</text>
		<text name="FromSaleOrder">មកពីបញ្ជាលក់</text>
		<text name="FromSaleReturn">មកពីត្រឡប់ទំនិញលក់</text>
		<text name="FromPurchaseOrder">មកពីបញ្ជាទិញ</text>
		<text name="FromPurchaseReturn">មកពីត្រឡប់ទំនិញទិញ</text>
		<text name="FromInventoryPurchase">មកពីទំនិញទិញ</text>
		<text name="CreateAccountBill">បង្កើវិក្កយបត្រចំណាយ</text>
		<text name="CreateAccountInovice">បង្កើតវិក្កយបត្រចំណូល</text>
		<text name="CreateDebitNote">បង្កើតបុងជំពាក់</text>
		<text name="CreateAdvancePayment">បង្កើបុងត្រូវចំណាយ</text>
		<text name="Renew">បន្តជាថ្មី</text>
		<text name="Reorder">កុំហ្មងជាថ្មី</text>
		<text name="ConvertToBill">បំប្លែងជាវិក្កយបត្រទិញ</text>
		<text name="VendorList">តារាងអ្នកផ្គត់ផ្គង់</text>
		<text name="VendorGroups">ក្រុមអ្នកផ្គត់ផ្គង់</text>
		<text name="VendorGroup">ក្រុមអ្នកផ្គត់ផ្គង់</text>
		<text name="PaymentHistory">ប្រវត្តិបង់ប្រាក់</text>
		<text name="Sales">លក់</text>
		<text name="FromInventorySale">មកពីទំនិញលក់</text>
		<text name="FromInventorySaleReturn">មកពីត្រឡប់ទំនិញលក់</text>
		<text name="CreateSaleReturn">បង្កើតត្រឡប់ទំនិញលក់</text>
		<text name="CreateSaleInvoice">បង្កើតវក្កយបត្រលក់</text>
		<text name="CreateCustomerDiposit">បង្កើត</text>
		<text name="CreateCreditNote">បង្កើបុងត្រូវទទួល</text>
		<text name="ConvertToContract">បំប្លែងជាកិច្ចសន្យា</text>
		
		<text name="CreditSale">លក់ជំពាក់</text>
		<text name="Split">បំបែក</text>
		<text name="Merge">ភ្ជាប់</text>
		<text name="Refund">សងប្រាក់វិញ</text>
		<text name="PayBill">ទូទាត់វិក្កយបត្រ</text>
		<text name="FromInventoryPurchaseReturn">មកពីត្រឡប់ទំនិញទិញ</text>
		<text name="CreatePurchaseReturn">បង្កើតត្រឡប់ទំនិញទិញ</text>
		<text name="CreatePurchaseBill">បង្កើតវិក្កយបត្រទិញ</text>
		<text name="CreateSlaeInvoice">បង្កើតវិក្កយបត្រលក់</text>
		<text name="CreateCustomerDeposit">បង្កើតលុយកក់អតិថិជន</text>
		<text name="ProductionList">តារាងផលិតកម្ម</text>
		<text name="LocationList">តារាងទីតាំង</text>
		<text name="Common">ទូទៅ</text>
		<text name="CreateFolder">បង្កើតថតឯកសារ</text>
		<text name="EditFolder">កែប្រែថតឯកសារ</text>
		<text name="RenameFolder">ប្ដូរឈ្មោះថតឯកសារ</text>
		<text name="DeleteFolder">លុបថតឯកសារ</text>
		<text name="ChangeFolder">ប្ដូរថតឯកសារ</text>
		<text name="Folders">ថតឯកសារ</text>
		<text name="Folder">ថតឯកសារ</text>
		<text name="FileList">តារាងឯកសារ</text>
		<text name="IssueTransfers">ផ្ទេរចេញ</text>
		<text name="IssueTransfer">ផ្ទេរចេញ</text>
		<text name="ReceiptTransfers">ផ្ទេរចូល</text>
		<text name="ReceiptTransfer">ផ្ទេរចូល</text>
		<text name="InventoryTransactions">ប្រតិបត្តិការស្តុក</text>
		<text name="IssueAdjustments">កែតម្រូវបញ្ចេញ</text>
		<text name="IssueAdjustment">កែតម្រូវបញ្ចេញ</text>
		<text name="ReceiptAdjustments">កែតម្រូវបញ្ចូល</text>
		<text name="ReceiptAdjustment">កែតម្រូវបញ្ចូល</text>
		<text name="ReceiptOthers">ទទួលផ្សេងៗ</text>
		<text name="ReceiptOther">ទទួលផ្សេងៗ</text>
		<text name="IssueOthers">បញ្ចេញផ្សេងៗ</text>
		<text name="IssueOther">បញ្ចេញផ្សេងៗ</text>
		<text name="IsRequired">{0} ត្រូវតែបំពេញ</text>
		<text name="Select">ជ្រើសរើស</text>
		<text name="Select_">ជ្រើសរើស {0}</text>
		<text name="DisableWarningMessage">តើអ្នកចង់ផ្អាកបណ្ដោះចំពោះ {0} មែនទេ</text>
		<text name="EnableWarningMessage">តើអ្នកចង់ដំណើរការ {0} មែនទេ</text>
		<text name="ActivateWarningMessage">តើអ្នកចង់ដំណើរការ {0} មែនទេ</text>
		<text name="DeactivateWarningMessage">តើអ្នកចង់បញ្ឈប់ដំណើរការ {0} មែនទេ</text>
		<text name="DefaultWarningMessage">តើអ្នកចង់កំណត់ {0} ជាលំនាំដើមមែនទេ</text>
		<text name="Default">លំនាំដើម</text>
		<text name="Symbol">និមិត្តសញ្ញា</text>
		<text name="Activate">ដំណើរការ</text>
		<text name="Deactivate">បញ្ឈប់ដំណើរការ</text>
		<text name="CannotBeGreaterThan">{0} មិនអាចធំជាង {1}</text>
		<text name="CannotBeLessThan">{0} មិនអាចតិចជាង {1}</text>
		<text name="CannotBeMoreThan">{0} មិនអាចលើសពី {1}</text>
		<text name="CannotBeSmallerThan">{0} មិនអាចតូចជាង {1}</text>
		<text name="CannotBeEqualTo">{0} មិនអាចស្មើនឹង {1}</text>
		<text name="MustBeGreaterThan">{0} ត្រូវតែធំជាង {1}</text>
		<text name="MustBeLessThan">{0} ត្រូវតែតិចជាង {1}</text>
		<text name="MustBeMoreThan">{0} ត្រូវតែច្រើនជាង {1}</text>
		<text name="MustBeSmallerThan">{0} ត្រូវតែតូចជាង {1}</text>
		<text name="MustBeEqualTo">{0} ត្រូវតែស្មើនឹង {1}</text>
		<text name="CanNotBeEmpty">{0} មិនអាចទទេ</text>
		<text name="Characters">តួរអក្សរ</text>
		<text name="Characters_">{0} តួរអក្សរ</text>
		<text name="UseEmail">ប្រើប្រាស់អ៊ីម៉ែល</text>
		<text name="Find">ស្វែងរក</text>
		<text name="FindUsers">ស្វែងរកអ្នកប្រើប្រាស់</text>
		<text name="FindEditions">ស្វែងរកកញ្ចប់កម្មវិធី</text>
		<text name="FindLocations">ស្វែងរកទីតាំង</text>

		<text name="Duplicate">{0} ជាន់គ្នា</text>
		<text name="LocationCode">កូដទីតាំង</text>
		<text name="CannotBeEmpty">{0} មិនអាចទទេ</text>
		<text name="IsNotValid">{0} មិនត្រឹមត្រូវ</text>
		<text name="Invalid">{0} មិនត្រឹមត្រូវ</text>
		<text name="OutOfRange">{0} លើសខ្ទង់ដែលបានកំណត់</text>
		<text name="IsNotEditable">{0} នេះមិនត្រូវបានអនុញ្ញាតឱ្យកែប្រែទេ</text>
		<text name="IsNotDeletable">{0} នេះមិនត្រូវបានអនុញ្ញាតឱ្យលុបទេ</text>
		<text name="View_">ពិនិត្យ {0}</text>
		<text name="Create_">បង្កើត {0}</text>
		<text name="Update_">កែប្រែ {0}</text>
		<text name="Edit_">កែប្រែ {0}</text>
		<text name="Add_">បន្ថែម {0}</text>
		<text name="PleaseEnterDeleteToConfirm">សូមបញ្ចូលពាក្យថា "Delete" ដើម្បីបញ្ជាក់</text>
		<text name="ConfirmDelete">បញ្ជាក់ការលុប</text>
		<text name="SaveNew">រក្សាទុកបង្កើតថ្មី</text>
		<text name="SaveNext">រក្សាទុកនិងបន្ត</text>
		<text name="No.">ល.រ</text>
		<text name="Code">លេខកូដ</text>
		<text name="Code_">លេខកូដ{0}</text>
		<text name="CreationTime">ម៉ោងបង្កើត</text>
		<text name="LastModificationTime">ម៉ោងកែប្រែ</text>
		<text name="CreatedBy">បង្កើតដោយ</text>
		<text name="LastModifiedBy">កែប្រែដោយ</text>
		<text name="Editable">អាចកែបាន</text>
		<text name="Deletable">អាចលុបបាន</text>
		<text name="Latitude">រយៈទទឹង</text>
		<text name="Longitude">រយៈបណ្ដោយ</text>
		<text name="Id">លេខសម្គាល់</text>
		<text name="UserInfo">ព័ត៌មានអ្នកប្រើប្រាស់</text>
		<text name="Created">អ្នកបង្កើត</text>
		<text name="Modified">អ្នកកែប្រែ</text>
		<text name="Name_">ឈ្មោះ{0}</text>
		<text name="CannotEdit">មិនអាចកែប្រែ</text>
		<text name="CannotDelete">មិនអាចលុប</text>
		<text name="DownloadTemplate">ទាញយកគម្រូ</text>
		<text name="SelectTemplate">ជ្រើសរើសគម្រូ</text>
		<text name="True">ពិត</text>
		<text name="False">មិនពិត</text>
		<text name="NoImportTemplateTemplateMessage">បើអ្នកមិនមានទម្រង់គម្រូ សូមចុចប៊ូតុង "ទាញយកគម្រូ" ខាងក្រោម។</text>
		<text name="PleaseSelect_">សូមជ្រើសរើស {0}</text>
		<text name="PleaseEnter_">សូមបំពេញ {0}</text>
		<text name="Exclude">ដកចេញ</text>
		<text name="FindCurrencies">ស្វែងរករូបិយបណ្ណ</text>
		<text name="UISettings">កំណត់រាងស្បែក</text>
		<text name="FindCountries">ស្វែងរកប្រទេស</text>
		<text name="CityProvince">ខេត្ត/ក្រុង</text>
		<text name="FindCityProvinces">ស្វែងរកខេត្ត/ក្រុង</text>
		<text name="KhanDistrict">ស្រុក/ខណ្ឌ</text>
		<text name="FindKhanDistricts">ស្វែងរកស្រុក/ខណ្ឌ</text>
		<text name="SangkatCommune">ឃុំ/សង្កាត់</text>
		<text name="FindSangkatCommunes">ស្វែងរកឃុំ/សង្កាត់</text>
		<text name="Village">ភូមិ</text>
		<text name="FindVillages">ស្វែងរកភូមិ</text>
		<text name="PhonePrefix">កូដទូរសព្ទ</text>
		<text name="GeoCode">កូដតំបន់</text>
		<text name="Error">កំហុស</text>
		<text name="ISO">ISO</text>
		<text name="ISO2">ISO2</text>
		<text name="ISO3">ISO3</text>
		<text name="TenantManagement">គ្រប់គ្រងអ្នកជាវ</text>
		<text name="UserManagement">គ្រប់គ្រង់អ្នកប្រើប្រាស់</text>
		<text name="Security">សុវត្ថិភាព</text>
		<text name="General">ទូទៅ</text>
		<text name="Billing">វិក្កយបត្រ</text>
		<text name="Timezone">ល្វែងម៉ោង</text>
		<text name="AllowSelfRegistration">អនុញ្ញាតចុះឈ្មោះខ្លួនឯង</text>
		<text name="IfYouDisableThisTenantsWillOnlyBeAddedByAdminUsingTenantManagementPage">If you disable this tenants will only be added by admin using tenant management page</text>
		<text name="IsNewRegisteredTenantActiveByDefault">Is new registered tenant active by default</text>
		<text name="IfYouDisableThisNewTenantsWillNotBeActiveAndCanNotLoginUntilAdminManuallyActivateTheAccount">If you disable this new tenants will not be active and can not login until admin manually activate the account</text>
		<text name="UseCaptchaOnRegistration">Use captcha on registration</text>
		<text name="IsEmailConfirmationRequiredForLogin">Is email confirmation required for Login</text>
		<text name="SMSVerificationEnabled">SMS verification enabled</text>
		<text name="PasswodComplexitySettings">Passwod complexity settings</text>
		<text name="UseDefaultPasswordComplexitySettings">Use default password complexity settings</text>
		<text name="RequireDigit">មានលេខ</text>
		<text name="RequireLowercase">មានអក្សរតូច</text>
		<text name="RequireUppercase">មានអក្សរធំ</text>
		<text name="RequireNonAlphanumeric">មានសញ្ញាផ្សេង (!@#$*...)</text>
		<text name="TwoFactorLogin">Two Factor Login</text>
		<text name="EnableTwoFactorLogin">Enable Two Factor Login</text>
		<text name="EnabledForApplication">Enabled For Application</text>
		<text name="EmailProviderEnabled">Email Provider Enabled</text>
		<text name="SmsProviderEnabled">Sms Provider Enabled</text>
		<text name="GoogleAuthenticatorEnabled">Google Authenticator Enabled</text>
		<text name="RememberBrowserEnabled">Remember Browser Enabled</text>
		<text name="IfYouAllowsThisUsersCanSelectToRememberBrowserToSkipSecondTimeTwoFactorLoginForTheSameBrowser">If you allows this users can select to remember browser to skip second time Two Factor Login for the same browser</text>
		<text name="UserLockOut">User Lock Out</text>
		<text name="EnableUserLockOut">Enable User Lock Out</text>
		<text name="MaxFailedAccessAttemptsBeforeLockout">Max failed access attempts before Lockout </text>
		<text name="DefaultAccountLockoutSeconds">Default account Lockout seconds</text>
		<text name="DefaultFromDisplayName">Default From Display Name</text>
		<text name="DefaultFromAddress">Default From Address</text>
		<text name="Host">Host</text>
		<text name="Port">Port</text>
		<text name="SSLEnable">SSL Enable</text>
		<text name="LegalName">ឈ្មោះចុះបញ្ជី</text>
		<text name="Address">អាសយដ្ឋាន</text>
		<text name="ContactAddress">អាសយដ្ឋានទំនាក់ទំនង</text>
		<text name="BillingAddress">អាសយដ្ឋានវិក្កយបត្រ</text>
		<text name="ShippingAddress">អាសយដ្ឋានដឹកជញ្ជូន</text>
		<text name="SameAsBillingAddress">ដូចអាសយដ្ឋានវិក្កយបត្រ</text>
		<text name="PlaceOfBirth">ទីកន្លែងកំណើត</text>
		<text name="AlreadyHasMembers">{0} មានសមាជិកភាពហើយ</text>
		<text name="BusinessId">អក្សរកាត់</text>
		<text name="PhoneNumber">លេខទូរសព្ទ</text>
		<text name="Email">អ៊ីម៉ែល</text>
		<text name="Website">គេហទំព័រ</text>
		<text name="TaxRegistrationNumber">លេខចុះបញ្ជីពន្ធ</text>
		<text name="TaxNumber">លេខបញ្ជីពន្ធ</text>
		<text name="PostalCode">កូដប្រៃសណីយ</text>
		<text name="Street">លេខផ្លូវ</text>
		<text name="HouseNo">លេខផ្ទះ</text>
		<text name="IncorrectCaptchaAnswer">Captcha មិនត្រឹមត្រូវ</text>
		<text name="CountryISO">ប្រទេស ISO</text>
		<text name="ProvinceISO">ខេត្ត ISO</text>
		<text name="Copyright">រក្សាសិទ្ធិ</text>
		<text name="RegionCountry">តំបន់ប្រទេស</text>
		<text name="Next">បន្ទាប់</text>
		<text name="Previous">បកក្រោយ</text>
		<text name="BusinessStartDate">ថ្ងៃផ្តើមអាជីវកម្ម</text>
		<text name="Rounding">កាត់ខ្ទង់</text>
		<text name="Rounding_">កាត់ខ្ទង់{0}</text>
		<text name="Price">តម្លៃ</text>
		<text name="Cost">តម្លៃ</text>
		<text name="Choose">ជ្រើសរើស</text>
		<text name="Choose_">ជ្រើសរើស{0}</text>
		<text name="Photo">រូបភាព</text>
		<text name="Logo">ឡូហ្កូ</text>
		<text name="MultiBranchesEnable">ប្រើមុខងារ​ច្រើនសាខា</text>
		<text name="MultiCurrencyEnable">ប្រើមុខងាររូបិយបណ្ណច្រើន</text>
		<text name="LineDiscountEnable">ប្រើមុខងារបញ្ចុះតម្លៃតាមជួរ</text>
		<text name="TotalDiscountEnable">ប្រើមុខងារបញ្ចុះតម្លៃចុងក្រោយ</text>
		<text name="CustomTransactionNoEnable">ប្រើមុខងារដាក់លេខឯកសារខ្លួនឯង</text>
		<text name="CustomNo">ដាក់លេខឯកសារខ្លួនឯង</text>
		<text name="TransactionNo">លេខប្រតិបត្តិការ</text>
		<text name="ClassEnable">ប្រើថ្នាក់</text>
		<text name="ContactAddressLevel">កម្រិតអាសយដ្ឋានទំនាក់ទំនង</text>
		<text name="RequiredReference">ត្រូវបំពេញឯកសារយោង</text>

		<text name="GeneralJournal">ទិនានុប្បវត្តិ</text>
		<text name="CashIn">លុយ​ចូល</text>
		<text name="CashOut">លុយចេញ</text>
		<text name="CashTransfer">ផ្ទេរប្រាក់</text>
		<text name="CashExchange">ដូរលុយ</text>
		<text name="PurchaseReturn">ត្រឡប់ទំនិញទិញ</text>
		<text name="DebitNote">ចំណាំឥណពន្ធ</text>
		<text name="VendorRefund">ត្រឡប់លុយពីអ្នកផ្គត់ផ្គង់</text>
		<text name="CreditNote">ចំណាំឥណទាន</text>
		<text name="CustomerRefund">ត្រឡប់លុយឱ្យអតិថិជន</text>
		<text name="ItemReceipt">ទទួលទំនិញ</text>
		<text name="ItemIssue">បញ្ចេញទំនិញ</text>
		<text name="ItemTransfer">ផ្ទេរទំនិញ</text>
		<text name="ItemExchange">ដូរទំនិញ</text>
		<text name="PhysicalCount">រាប់ស្តុកជាក់ស្ដែង</text>
		<text name="TransactionType">ប្រភេទប្រតិបត្តិការ</text>
		<text name="ParentAccount">គណនីមេ</text>
		<text name="AccountType">ប្រភេទគណនី</text>
		<text name="SubAccountType">ប្រភេទគណនីរង</text>
		<text name="FindChartOfAccounts">ស្វែងរកគណនី</text>
		<text name="CustomAccountCodeEnable">ដាក់កូដគណនីខ្លួនឯង</text>
		<text name="SubAccountCannotUseAsParent">គណនីរងមិនអាចប្រើជាគណនីមេបានទេ</text>
		<text name="PurchaseAccount">គណនីទិញចូល</text>
		<text name="SaleAccount">គណនីលក់ចេញ</text>
		<text name="FindUnits">ស្វែងរកខ្នាត</text>
		<text name="ItemBrands">ម៉ាក</text>
		<text name="ItemBrand">ម៉ាក</text>
		<text name="FindItemBrands">ស្វែងរកម៉ាក</text>
		<text name="ItemGrades">ថ្នាក់</text>
		<text name="ItemGrade">ថ្នាក់</text>
		<text name="FindItemGrades">ស្វែងរកថ្នាក់</text>
		<text name="Models">គម្រូ</text>
		<text name="ItemModels">គម្រូ</text>
		<text name="ItemModel">គម្រូ</text>
		<text name="FindItemModels">ស្វែងរកគម្រូ</text>
		<text name="Series">ស៊េរី</text>
		<text name="ItemSeries">ស៊េរី</text>
		<text name="ItemSerie">ស៊េរី</text>
		<text name="FindItemSeries">ស្វែងរកស៊េរី</text>
		<text name="ItemSizes">ទំហំ</text>
		<text name="ItemSize">ទំហំ</text>
		<text name="FindItemSizes">ស្វែងរកទំហំ</text>
		<text name="FindColorPatterns">ស្វែងរកពណ៌ផ្ទៃ</text>
		<text name="CPUs">CPU</text>
		<text name="CPU">CPU</text>
		<text name="FindCPUs">ស្វែងរក CPU</text>
		<text name="RAMs">RAM</text>
		<text name="RAM">RAM</text>
		<text name="FindRAMs">ស្វែងរក RAM</text>
		<text name="VGAs">VGA</text>
		<text name="VGA">VGA</text>
		<text name="FindVGAs">ស្វែងរក VGA</text>
		<text name="HDDs">HDD</text>
		<text name="HDD">HDD</text>
		<text name="FindHDDs">ស្វែងរក HDD</text>
		<text name="Screens">អេក្រង់</text>
		<text name="Screen">អេក្រង់</text>
		<text name="FindScreens">ស្វែងរកអេក្រង់</text>
		<text name="Cameras">កាមេរ៉ា</text>
		<text name="Camera">កាមេរ៉ា</text>
		<text name="FindCameras">ស្វែងរកកាមេរ៉ា</text>
		<text name="Batteries">ថ្ម</text>
		<text name="Battery">ថ្ម</text>
		<text name="FindBatteries">ស្វែងរកថ្ម</text>
		<text name="FindFieldAs">ស្វែងរកជួរ A</text>
		<text name="FindFieldBs">ស្វែងរកជួរ B</text>
		<text name="FindFieldCs">ស្វែងរកជួរ C</text>
		<text name="FindItems">ស្វែងរកទំនិញ</text>
		<text name="FindItemGroups">ស្វែងរកក្រុមទំនិញ</text>
	</texts>
</localizationDictionary>
